dash_particles/DashParticles.py
dash_particles/__init__.py
dash_particles/_imports_.py
dash_particles/async-DashParticles.js
dash_particles/async-DashParticles.js.map
dash_particles/dash_particles.min.js
dash_particles/dash_particles.min.js.map
dash_particles/metadata.json
dash_particles/package-info.json
dash_particles-0.0.1.dist-info/LICENSE
dash_particles-0.0.1.dist-info/METADATA
dash_particles-0.0.1.dist-info/WHEEL
dash_particles-0.0.1.dist-info/top_level.txt
dash_particles-0.0.1.dist-info/RECORD
