Metadata-Version: 2.2
Name: dash_particles
Version: 0.0.1
Summary: This is Particles.js, but in Dash!
Author: Jeff Gallini <gallinij@gmail.com>
License: MIT
Classifier: Framework :: Dash
License-File: LICENSE
Dynamic: author
Dynamic: classifier
Dynamic: description
Dynamic: description-content-type
Dynamic: license
Dynamic: summary
